ochrona/__init__.py
ochrona/__main__.py
ochrona/const.py
ochrona/exceptions.py
ochrona/cli/__init__.py
ochrona/cli/cli.py
ochrona/client/__init__.py
ochrona/client/pypi.py
ochrona/config/__init__.py
ochrona/config/config.py
ochrona/db/__init__.py
ochrona/db/db.py
ochrona/eval/__init__.py
ochrona/eval/eval.py
ochrona/eval/lexer.py
ochrona/eval/models.py
ochrona/eval/parser.py
ochrona/eval/tokens.py
ochrona/eval/policy/__init__.py
ochrona/eval/policy/evaluate.py
ochrona/eval/policy/validator.py
ochrona/eval/vuln/__init__.py
ochrona/eval/vuln/evaluate.py
ochrona/file/__init__.py
ochrona/file/file_handler.py
ochrona/importer/__init__.py
ochrona/importer/import_wrapper.py
ochrona/log/__init__.py
ochrona/log/logger.py
ochrona/model/__init__.py
ochrona/model/confirmed_vulnerability.py
ochrona/model/dependency.py
ochrona/model/dependency_set.py
ochrona/model/policy_violation.py
ochrona/model/sast_violation.py
ochrona/parser/__init__.py
ochrona/parser/conda.py
ochrona/parser/constraints.py
ochrona/parser/pipfile.py
ochrona/parser/poetry.py
ochrona/parser/requirements.py
ochrona/parser/setup_.py
ochrona/parser/tox.py
ochrona/reporter/__init__.py
ochrona/reporter/reporter.py
ochrona/reporter/reports/__init__.py
ochrona/reporter/reports/base.py
ochrona/reporter/reports/basic.py
ochrona/reporter/reports/full.py
ochrona/reporter/reports/html.py
ochrona/reporter/reports/json.py
ochrona/reporter/reports/xml.py
ochrona/sast/eval.py
ochrona/sast/plugins/base.py
ochrona/sast/plugins/flask_debug.py
ochrona/sast/plugins/pyyaml_load.py
ochrona/sast/plugins/requests_verify_false.py
ochrona/sast/plugins/stdlib_assert.py
ochrona/sast/plugins/stdlib_eval_call.py
ochrona/sast/plugins/stdlib_exec_call.py
ochrona/sast/plugins/stdlib_pickle_loads.py
ochrona/sast/plugins/stdlib_tarfile_extractall.py
ochrona/sast/plugins/stdlib_xml_parse.py
ochrona/sbom/__init__.py
ochrona/sbom/specs/cyclonedx.py
ochrona/schema/report.html.jinja
ochrona/schema/spdx_modified.json
ochrona/utils/__init__.py
ochrona-2.0.2.dist-info/LICENSE
ochrona-2.0.2.dist-info/METADATA
ochrona-2.0.2.dist-info/WHEEL
ochrona-2.0.2.dist-info/entry_points.txt
ochrona-2.0.2.dist-info/top_level.txt
ochrona-2.0.2.dist-info/RECORD
