Metadata-Version: 2.1
Name: ochrona
Version: 2.0.2
Summary: Ochrona checks your open source dependencies for vulnerabilities and policy violations.
Home-page: https://github.com/ochronasec/ochrona-cli
Author: Andrew Scott
Author-email: andrew@ochrona.dev
License: MIT
Keywords: ochrona,security,dependencies,vulnerability,testing,sca,sast
Classifier: Development Status :: 4 - Beta
Classifier: Environment :: Console
Classifier: Intended Audience :: Developers
Classifier: License :: OSI Approved :: MIT License
Classifier: Natural Language :: English
Classifier: Operating System :: OS Independent
Classifier: Programming Language :: Python :: 3.7
Classifier: Programming Language :: Python :: 3.8
Classifier: Programming Language :: Python :: 3.9
Classifier: Topic :: Software Development :: Quality Assurance
Classifier: Topic :: Software Development :: Build Tools
Classifier: Topic :: Utilities
Classifier: Topic :: Security
Classifier: Typing :: Typed
Requires-Python: >=3.7
License-File: LICENSE
Requires-Dist: click (>=7.1.2)
Requires-Dist: pyyaml (>=5.4.1)
Requires-Dist: requests (>=2.25.0)
Requires-Dist: toml (>=0.10.2)
Requires-Dist: python-dateutil (>=2.8.1)
Requires-Dist: tarsafe (>=0.0.3)
Requires-Dist: packaging (>=20.4)
Requires-Dist: requests-cache (>=0.5.2)
Requires-Dist: appdirs (>=1.4.4)
Requires-Dist: rich (>=10.16.1)
Requires-Dist: Jinja2 (>=3.0.3)
